column/__init__.py
column/column.py
modelpyxl/__init__.py
modelpyxl/column.py
modelpyxl/modelpyxl.py
modelpyxl-0.0.53.dist-info/LICENSE
modelpyxl-0.0.53.dist-info/METADATA
modelpyxl-0.0.53.dist-info/WHEEL
modelpyxl-0.0.53.dist-info/top_level.txt
modelpyxl-0.0.53.dist-info/RECORD
